django_helpdesk-2.1.0.dist-info/METADATA
django_helpdesk-2.1.0.dist-info/WHEEL
django_helpdesk-2.1.0.dist-info/entry_points.txt
django_helpdesk-2.1.0.dist-info/licenses/LICENSE
django_helpdesk-2.1.0.dist-info/licenses/LICENSE.3RDPARTY
helpdesk/__init__.py
helpdesk/admin.py
helpdesk/apps.py
helpdesk/decorators.py
helpdesk/email.py
helpdesk/exceptions.py
helpdesk/fixtures/emailtemplate.json
helpdesk/forms.py
helpdesk/lib.py
helpdesk/locale/ar/LC_MESSAGES/django.mo
helpdesk/locale/ar/LC_MESSAGES/django.po
helpdesk/locale/ca/LC_MESSAGES/django.mo
helpdesk/locale/ca/LC_MESSAGES/django.po
helpdesk/locale/cs/LC_MESSAGES/django.mo
helpdesk/locale/cs/LC_MESSAGES/django.po
helpdesk/locale/de/LC_MESSAGES/django.mo
helpdesk/locale/de/LC_MESSAGES/django.po
helpdesk/locale/el/LC_MESSAGES/django.mo
helpdesk/locale/el/LC_MESSAGES/django.po
helpdesk/locale/en/LC_MESSAGES/django.mo
helpdesk/locale/en/LC_MESSAGES/django.po
helpdesk/locale/es/LC_MESSAGES/django.mo
helpdesk/locale/es/LC_MESSAGES/django.po
helpdesk/locale/es_CO/LC_MESSAGES/django.mo
helpdesk/locale/es_CO/LC_MESSAGES/django.po
helpdesk/locale/es_MX/LC_MESSAGES/django.mo
helpdesk/locale/es_MX/LC_MESSAGES/django.po
helpdesk/locale/fa_IR/LC_MESSAGES/django.mo
helpdesk/locale/fa_IR/LC_MESSAGES/django.po
helpdesk/locale/fi/LC_MESSAGES/django.mo
helpdesk/locale/fi/LC_MESSAGES/django.po
helpdesk/locale/fr/LC_MESSAGES/django.mo
helpdesk/locale/fr/LC_MESSAGES/django.po
helpdesk/locale/he_IL/LC_MESSAGES/django.mo
helpdesk/locale/he_IL/LC_MESSAGES/django.po
helpdesk/locale/hr/LC_MESSAGES/django.mo
helpdesk/locale/hr/LC_MESSAGES/django.po
helpdesk/locale/hu/LC_MESSAGES/django.mo
helpdesk/locale/hu/LC_MESSAGES/django.po
helpdesk/locale/it/LC_MESSAGES/django.mo
helpdesk/locale/it/LC_MESSAGES/django.po
helpdesk/locale/lv/LC_MESSAGES/django.mo
helpdesk/locale/lv/LC_MESSAGES/django.po
helpdesk/locale/nb_NO/LC_MESSAGES/django.mo
helpdesk/locale/nb_NO/LC_MESSAGES/django.po
helpdesk/locale/pl/LC_MESSAGES/django.mo
helpdesk/locale/pl/LC_MESSAGES/django.po
helpdesk/locale/pt_BR/LC_MESSAGES/django.mo
helpdesk/locale/pt_BR/LC_MESSAGES/django.po
helpdesk/locale/pt_PT/LC_MESSAGES/django.mo
helpdesk/locale/pt_PT/LC_MESSAGES/django.po
helpdesk/locale/ru/LC_MESSAGES/django.mo
django_helpdesk-2.1.0.dist-info/RECORD
