Metadata-Version: 2.1
Name: django-helpdesk
Version: 2.1.0
Summary: Django-powered ticket tracker for your helpdesk
Keywords: django,helpdesk,django-helpdesk,tickets,incidents,cases,bugs,track,support
Author-Email: Ross Poulton <ross@rossp.org>
Maintainer: David Vadnais - Github@DavidVadnais, Ben - Github:@Benbb96
Maintainer-Email: Christopher Broderick <uhurusurfa@gmail.com>
License: BSD-3-Clause
Classifier: Development Status :: 5 - Production/Stable
Classifier: Environment :: Web Environment
Classifier: Framework :: Django
Classifier: Framework :: Django :: 4.0
Classifier: Framework :: Django :: 5.0
Classifier: Intended Audience :: Customer Service
Classifier: Natural Language :: English
Classifier: Operating System :: OS Independent
Classifier: Programming Language :: Python
Classifier: Programming Language :: Python :: 3
Classifier: Programming Language :: Python :: 3.9
Classifier: Programming Language :: Python :: 3.10
Classifier: Programming Language :: Python :: 3.11
Classifier: Programming Language :: Python :: 3.12
Classifier: Programming Language :: Python :: 3.13
Classifier: Programming Language :: Python :: 3.14
Classifier: Topic :: Office/Business
Classifier: Topic :: Software Development :: Bug Tracking
Classifier: Topic :: Software Development :: Libraries :: Python Modules
Project-URL: Homepage, https://github.com/django-helpdesk/django-helpdesk
Requires-Python: >=3.9
Requires-Dist: django>=4.2
Requires-Dist: django-bootstrap4-form
Requires-Dist: celery
Requires-Dist: email-reply-parser
Requires-Dist: akismet
Requires-Dist: markdown
Requires-Dist: beautifulsoup4
Requires-Dist: lxml
Requires-Dist: pytz
Requires-Dist: djangorestframework
Requires-Dist: django-model-utils
Requires-Dist: django-cleanup
Requires-Dist: oauthlib
Requires-Dist: requests-oauthlib
Requires-Dist: requests
Requires-Dist: requests_oauthlib
Requires-Dist: setuptools
Provides-Extra: teams
Requires-Dist: pinax_teams; extra == "teams"
